[
    {
        "id": "2603.25746v1",
        "title": "ShotStream: Streaming Multi-Shot Video Generation for Interactive Storytelling",
        "score": 9.5,
        "reason": "Turns multi-shot video generation into a low-latency streaming problem and makes interactive narrative control practical on a single GPU.",
        "categories": ["cs.CV"],
        "published": "2026-03-26T17:59:59Z",
        "pdf_url": "https://arxiv.org/pdf/2603.25746v1"
    },
    {
        "id": "2603.25744v1",
        "title": "MuRF: Unlocking the Multi-Scale Potential of Vision Foundation Models",
        "score": 9.4,
        "reason": "A simple training-free multi-resolution fusion trick that upgrades frozen vision foundation models across tasks and model families.",
        "categories": ["cs.CV"],
        "published": "2026-03-26T17:59:58Z",
        "pdf_url": "https://arxiv.org/pdf/2603.25744v1"
    },
    {
        "id": "2603.25730v1",
        "title": "PackForcing: Short Video Training Suffices for Long Video Sampling and Long Context Inference",
        "score": 9.4,
        "reason": "Pushes long-video diffusion much further with bounded KV-cache growth and large temporal extrapolation from short-video supervision.",
        "categories": ["cs.CV", "cs.AI"],
        "published": "2026-03-26T17:59:05Z",
        "pdf_url": "https://arxiv.org/pdf/2603.25730v1"
    },
    {
        "id": "2603.25741v1",
        "title": "Vega: Learning to Drive with Natural Language Instructions",
        "score": 9.3,
        "reason": "Combines language-conditioned world modeling and planning for personalized autonomous driving with a sizable new instruction dataset.",
        "categories": ["cs.CV", "cs.AI", "cs.RO"],
        "published": "2026-03-26T17:59:56Z",
        "pdf_url": "https://arxiv.org/pdf/2603.25741v1"
    },
    {
        "id": "2603.25719v1",
        "title": "Agent Factories for High Level Synthesis: How Far Can General-Purpose Coding Agents Go in Hardware Optimization?",
        "score": 9.3,
        "reason": "Shows coordinated general-purpose coding agents can deliver large hardware-design speedups without hardware-specific training.",
        "categories": ["cs.AI", "cs.AR", "cs.LG"],
        "published": "2026-03-26T17:57:50Z",
        "pdf_url": "https://arxiv.org/pdf/2603.25719v1"
    },
    {
        "id": "2603.25738v1",
        "title": "PSDesigner: Automated Graphic Design with a Human-Like Creative Workflow",
        "score": 9.2,
        "reason": "Moves beyond image generation into editable PSD-level automation by teaching models a more human design workflow.",
        "categories": ["cs.CV"],
        "published": "2026-03-26T17:59:51Z",
        "pdf_url": "https://arxiv.org/pdf/2603.25738v1"
    },
    {
        "id": "2603.25739v1",
        "title": "MegaFlow: Zero-Shot Large Displacement Optical Flow",
        "score": 9.2,
        "reason": "Uses pretrained global vision priors to get strong zero-shot large-displacement motion estimation without heavy task-specific tuning.",
        "categories": ["cs.CV"],
        "published": "2026-03-26T17:59:51Z",
        "pdf_url": "https://arxiv.org/pdf/2603.25739v1"
    },
    {
        "id": "2603.25737v1",
        "title": "Training the Knowledge Base through Evidence Distillation and Write-Back Enrichment",
        "score": 9.1,
        "reason": "Treats the RAG corpus itself as a trainable component and improves retrieval quality by writing distilled evidence back into the index.",
        "categories": ["cs.AI", "cs.CL", "cs.IR"],
        "published": "2026-03-26T17:59:49Z",
        "pdf_url": "https://arxiv.org/pdf/2603.25737v1"
    },
    {
        "id": "2603.25720v1",
        "title": "R-C2: Cycle-Consistent Reinforcement Learning Improves Multimodal Reasoning",
        "score": 9.1,
        "reason": "Uses cycle-consistent RL as a dense alignment signal to improve multimodal reasoning without extra labels.",
        "categories": ["cs.AI", "cs.CV"],
        "published": "2026-03-26T17:58:04Z",
        "pdf_url": "https://arxiv.org/pdf/2603.25720v1"
    },
    {
        "id": "2603.25723v1",
        "title": "Natural-Language Agent Harnesses",
        "score": 9.0,
        "reason": "Externalizes agent harness logic into portable natural-language artifacts, making controller design easier to transfer and study.",
        "categories": ["cs.CL", "cs.AI"],
        "published": "2026-03-26T17:58:15Z",
        "pdf_url": "https://arxiv.org/pdf/2603.25723v1"
    }
]
